structuinput/__init__.py
structuinput/main.py
structuinput/prompts.py
structuinput-2025.12.22085003.dist-info/METADATA
structuinput-2025.12.22085003.dist-info/WHEEL
structuinput-2025.12.22085003.dist-info/top_level.txt
structuinput-2025.12.22085003.dist-info/RECORD
