Metadata-Version: 2.4
Name: structuinput
Version: 2025.12.22085003
Summary: structuinput transforms natural language inputs into structured outputs like API templates, config files, and data schemas, streamlining development and integration.
Author-email: structuinput <hi@eugene.plus>
License: MIT
Project-URL: Homepage, https://github.com/chigwell/structuinput
Requires-Python: >=3.9
Requires-Dist: langchain-llm7>=0.0.0
Requires-Dist: llmatch-messages>=0.0.0
Requires-Dist: langchain-core>=0.3.0
